<?xml version = '1.0' encoding = 'UTF-8'?>
<TableProxyUDBv81 class="oracle.dbtools.crest.model.design.storage.udb.v81.TableProxyUDBv81" name="working_committee_head" directorySegmentName="seg_1" id="89A014E4-FFA3-B71A-5557-03C31D74E782">
<createdBy>alpha</createdBy>
<createdTime>2023-12-07 04:24:53 UTC</createdTime>
<ownerDesignName>dmd</ownerDesignName>
<summaryQueryChanged>false</summaryQueryChanged>
<summaryQueryDefinitionChanged>false</summaryQueryDefinitionChanged>
<columnProxies>
<ColumnProxy class="oracle.dbtools.crest.model.design.storage.udb.v81.ColumnProxyUDBv81" name="student_id" id="742B4B2A-7786-0561-2822-1395F928D06F">
<createdBy>alpha</createdBy>
<createdTime>2023-12-07 04:24:53 UTC</createdTime>
<ownerDesignName>dmd</ownerDesignName>
<generate>BY DEFAULT</generate>
<order>YES</order>
</ColumnProxy>
<ColumnProxy class="oracle.dbtools.crest.model.design.storage.udb.v81.ColumnProxyUDBv81" name="role_id" id="9179F736-89F6-BAB2-A9C2-0C8E9F603170">
<createdBy>alpha</createdBy>
<createdTime>2023-12-07 04:24:53 UTC</createdTime>
<ownerDesignName>dmd</ownerDesignName>
<generate>BY DEFAULT</generate>
<order>YES</order>
</ColumnProxy>
<ColumnProxy class="oracle.dbtools.crest.model.design.storage.udb.v81.ColumnProxyUDBv81" name="id" id="AAFD37DA-E932-3F69-2C96-61DD8FC9513E">
<createdBy>alpha</createdBy>
<createdTime>2023-12-07 04:24:53 UTC</createdTime>
<ownerDesignName>dmd</ownerDesignName>
<generate>BY DEFAULT</generate>
<order>YES</order>
</ColumnProxy>
</columnProxies>
<foreignKeys>
<ForeignKey class="oracle.dbtools.crest.model.design.storage.udb.v81.FKProxyUDBv81" name="working_committee_head_working_committee_role_FK" id="65DFC1F1-59B7-BCE7-94FD-0626F6091FE2">
<createdBy>alpha</createdBy>
<createdTime>2023-12-07 04:24:53 UTC</createdTime>
<ownerDesignName>dmd</ownerDesignName>
</ForeignKey>
<ForeignKey class="oracle.dbtools.crest.model.design.storage.udb.v81.FKProxyUDBv81" name="working_committee_head_student_FK" id="D0A6A875-AD87-6DD2-9ACE-E6FDFA31E312">
<createdBy>alpha</createdBy>
<createdTime>2023-12-07 04:24:53 UTC</createdTime>
<ownerDesignName>dmd</ownerDesignName>
</ForeignKey>
</foreignKeys>
</TableProxyUDBv81>
